.gitignore
AUTHORS
ChangeLog
LICENSE
README.md
setup.cfg
setup.py
data/examples/bots_useragents.txt
data/examples/parseurl.txt
logtools/__init__.py
logtools/_config.py
logtools/_filter.py
logtools/_filterbots.py
logtools/_flattenjson.py
logtools/_geoip.py
logtools/_join.py
logtools/_merge.py
logtools/_parse.py
logtools/_plot.py
logtools/_qps.py
logtools/_sample.py
logtools/_serve.py
logtools/_sumstat.py
logtools/_tail.py
logtools/_urlparse.py
logtools/join_backends.py
logtools/parsers.py
logtools/utils.py
logtools.egg-info/PKG-INFO
logtools.egg-info/SOURCES.txt
logtools.egg-info/dependency_links.txt
logtools.egg-info/entry_points.txt
logtools.egg-info/requires.txt
logtools.egg-info/top_level.txt
logtools.egg-info/zip-safe
logtools/test/__init__.py
logtools/test/test_logtools.py
scripts/aggregate
scripts/colsum
scripts/percentiles
scripts/triggered-regexp