Metadata-Version: 1.1
Name: logtools
Version: 0.8.7
Summary: Log analysis and filtering tools
Home-page: http://github.com/adamhadani/logtools
Author: Adam Ever-Hadani
Author-email: adamhadani@gmail.com
License: UNKNOWN
Keywords: logging,sampling,geoip,filterbots,aggregate,logparse,logmerge,logjoin,urlparse,logplot,qps,filter
Platform: UNKNOWN
Classifier: Programming Language :: Python
Classifier: Programming Language :: Python :: 2.6
Classifier: Development Status :: 5 - Production/Stable
Classifier: License :: OSI Approved :: Apache Software License
Classifier: Operating System :: POSIX
Classifier: Topic :: Internet :: Log Analysis
Classifier: Topic :: Scientific/Engineering :: Information Analysis
Classifier: Topic :: Text Processing :: Filters
Classifier: Topic :: Utilities
Classifier: Intended Audience :: Developers
Classifier: Intended Audience :: System Administrators
